Metadata-Version: 2.1
Name: oci-image
Version: 1.0.0
Summary: Helper for dealing with OCI Image resources in the charm operator framework
Home-page: https://github.com/juju-solutions/resource-oci-image
Author: Cory Johns
Author-email: johnsca@gmail.com
License: Apache License 2.0
Platform: UNKNOWN
